plugins/__init__.py
plugins/bbc_radio_1.py
plugins/example.py
plugins/plug_bbc_radio_1.py
radio/__init__.py
radio/app.py
radio/buffers.py
radio/commands.py
radio/log.py
radio/models.py
radio/player.py
radio/styles.py
radio/tui.py
zradio-0.0.dev1.dist-info/METADATA
zradio-0.0.dev1.dist-info/RECORD
zradio-0.0.dev1.dist-info/WHEEL
zradio-0.0.dev1.dist-info/entry_points.txt
zradio-0.0.dev1.dist-info/top_level.txt
