Metadata-Version: 2.1
Name: zradio
Version: 0.0.dev1
Summary: terminal radio.
Home-page: https://github.com/andreztz/zradio
Author: André P. Santos
Author-email: andreztz@gmail.com
License: MIT
Keywords: radio browser web terminal command line
Platform: UNKNOWN
Classifier: Development Status :: 1 - Planning
Classifier: Environment :: Console
Classifier: Programming Language :: Python :: 3.7
Requires-Dist: prompt-toolkit (==2.0.5)
Requires-Dist: python-vlc (==3.0.102)
Requires-Dist: pyradios (==0.0.9)
Requires-Dist: notify-send (==0.0.7)
